np_eyetracking/__init__.py
np_eyetracking/__main__.py
np_eyetracking/dlc_lims/__init__.py
np_eyetracking/dlc_lims/rig_geometry.py
np_eyetracking/dlc_lims/run_dlc.py
np_eyetracking/dlc_lims/session_to_nwb.py
np_eyetracking/dlc_lims/utils.py
np_eyetracking-0.1.2.dist-info/METADATA
np_eyetracking-0.1.2.dist-info/WHEEL
np_eyetracking-0.1.2.dist-info/top_level.txt
np_eyetracking-0.1.2.dist-info/RECORD
