Metadata-Version: 2.1
Name: np-eyetracking
Version: 0.1.2
Summary: Tools for generating eye-tracking data for .nwb creation.
Author-email: bjhardcastle <ben.hardcastle@alleninstitute.org>
License: MIT
Requires-Python: >=3.8
Requires-Dist: np-session (>=0.6.11)
Requires-Dist: allensdk (>=2.15.1)
Provides-Extra: dev
Requires-Dist: blue (>=0.9.1) ; extra == 'dev'
